README.md
setup.cfg
setup.py
seq_qc/__init__.py
seq_qc/demultiplex.py
seq_qc/pairs.py
seq_qc/qtrim.py
seq_qc/replicates.py
seq_qc/seq_io.py
seq_qc/structure.py
seq_qc/trim.py
seq_qc.egg-info/PKG-INFO
seq_qc.egg-info/SOURCES.txt
seq_qc.egg-info/dependency_links.txt
seq_qc.egg-info/entry_points.txt
seq_qc.egg-info/not-zip-safe
seq_qc.egg-info/requires.txt
seq_qc.egg-info/top_level.txt