Metadata-Version: 1.1
Name: seq-qc
Version: 2.0.4
Summary: utilities for performing various preprocessing steps on sequencing reads
Home-page: https://github.com/Brazelton-Lab/seq_qc/
Author: Christopher Thornton
Author-email: christopher.thornton@utah.edu
License: GPLv2
Download-URL: https://github.com/Brazelton-Lab/seq_qc/archive/v2.0.3.tar.gz
Keywords: bioinformatics sequence preprocessing quality control
Platform: UNKNOWN
Classifier: Development Status :: 4 - Beta
Classifier: Intended Audience :: Science/Research
Classifier: License :: OSI Approved :: GNU General Public License v2 (GPLv2)
Classifier: Natural Language :: English
Classifier: Operating System :: OS Independent
Classifier: Programming Language :: Python :: 3.4
Classifier: Topic :: Scientific/Engineering :: Bio-Informatics
Classifier: Topic :: Software Development :: Libraries :: Python Modules
